pyexcel_pdfr/__init__.py
pyexcel_pdfr/_version.py
pyexcel_pdfr/pdfr.py
pyexcel_pdfr-0.6.0.dist-info/LICENSE
pyexcel_pdfr-0.6.0.dist-info/METADATA
pyexcel_pdfr-0.6.0.dist-info/WHEEL
pyexcel_pdfr-0.6.0.dist-info/top_level.txt
pyexcel_pdfr-0.6.0.dist-info/RECORD
