Metadata-Version: 2.1
Name: pyexcel-pdfr
Version: 0.6.0
Summary: Read tables in pdf files using camelot for pyexcel community
Home-page: https://github.com/pyexcel/pyexcel-pdfr
Author: chfw
Author-email: info@pyexcel.org
License: New BSD
Download-URL: https://github.com/pyexcel/pyexcel-pdfr/archive/0.6.0.tar.gz
Keywords: python
Platform: UNKNOWN
Classifier: Topic :: Software Development :: Libraries
Classifier: Programming Language :: Python
Classifier: Intended Audience :: Developers
Classifier: Programming Language :: Python :: 2.6
Classifier: Programming Language :: Python :: 2.7
Classifier: Programming Language :: Python :: 3.3
Classifier: Programming Language :: Python :: 3.4
Classifier: Programming Language :: Python :: 3.5
Classifier: Programming Language :: Python :: 3.6
Classifier: Programming Language :: Python :: 3.7
Classifier: Programming Language :: Python :: 3.8
Requires-Dist: camelot-py[cv]
Requires-Dist: pyexcel-io (>=0.6.0)
